robo_orchard_lab/__init__.py
robo_orchard_lab/version.py
robo_orchard_lab/dataset/__init__.py
robo_orchard_lab/dataset/collates.py
robo_orchard_lab/dataset/datatypes/__init__.py
robo_orchard_lab/dataset/datatypes/camera.py
robo_orchard_lab/dataset/datatypes/geometry.py
robo_orchard_lab/dataset/datatypes/joint_state.py
robo_orchard_lab/dataset/datatypes/hg_features/__init__.py
robo_orchard_lab/dataset/datatypes/hg_features/base.py
robo_orchard_lab/dataset/datatypes/hg_features/tensor.py
robo_orchard_lab/dataset/embodiedscan/__init__.py
robo_orchard_lab/dataset/embodiedscan/embodiedscan_det_grounding_dataset.py
robo_orchard_lab/dataset/embodiedscan/metrics.py
robo_orchard_lab/dataset/embodiedscan/transforms.py
robo_orchard_lab/dataset/embodiedscan/utils.py
robo_orchard_lab/dataset/experimental/mcap/__init__.py
robo_orchard_lab/dataset/experimental/mcap/batch_split.py
robo_orchard_lab/dataset/experimental/mcap/data_record.py
robo_orchard_lab/dataset/experimental/mcap/messages.py
robo_orchard_lab/dataset/experimental/mcap/reader.py
robo_orchard_lab/dataset/experimental/mcap/writer.py
robo_orchard_lab/dataset/experimental/mcap/batch_decoder/__init__.py
robo_orchard_lab/dataset/experimental/mcap/batch_decoder/base.py
robo_orchard_lab/dataset/experimental/mcap/batch_decoder/camera.py
robo_orchard_lab/dataset/experimental/mcap/batch_decoder/joint_state.py
robo_orchard_lab/dataset/experimental/mcap/batch_decoder/pose.py
robo_orchard_lab/dataset/experimental/mcap/batch_decoder/tf.py
robo_orchard_lab/dataset/experimental/mcap/batch_encoder/__init__.py
robo_orchard_lab/dataset/experimental/mcap/batch_encoder/base.py
robo_orchard_lab/dataset/experimental/mcap/batch_encoder/camera.py
robo_orchard_lab/dataset/experimental/mcap/batch_encoder/joint_state.py
robo_orchard_lab/dataset/experimental/mcap/batch_encoder/pose.py
robo_orchard_lab/dataset/experimental/mcap/batch_encoder/tf.py
robo_orchard_lab/dataset/experimental/mcap/msg_converter/__init__.py
robo_orchard_lab-0.2.0.dist-info/licenses/LICENSE
robo_orchard_lab-0.2.0.dist-info/licenses/NOTICE
robo_orchard_lab-0.2.0.dist-info/METADATA
robo_orchard_lab-0.2.0.dist-info/WHEEL
robo_orchard_lab-0.2.0.dist-info/top_level.txt
robo_orchard_lab-0.2.0.dist-info/RECORD
